pybundle/__init__.py
pybundle/bundle_calibration.py
pybundle/core.py
pybundle/core_interpolation.py
pybundle/core_interpolation_numba.py
pybundle/mosaic.py
pybundle/pybundle.py
pybundle/super_res.py
pybundle/utility.py
PyFibreBundle-1.3.5.dist-info/LICENSE
PyFibreBundle-1.3.5.dist-info/METADATA
PyFibreBundle-1.3.5.dist-info/WHEEL
PyFibreBundle-1.3.5.dist-info/top_level.txt
PyFibreBundle-1.3.5.dist-info/RECORD
