Metadata-Version: 2.1
Name: PyFibreBundle
Version: 1.3.5
Summary: Image processing of images acquired through fibre imaging bundle, including core removal, mosaicing and super-resolution..
Author-email: Michael Hughes <m.r.hughes@kent.ac.uk>
License: MIT License
Project-URL: Homepage, https://github.com/MikeHughesKent/PyFibreBundle/
Keywords: fibre,fiber,bundle,endomicroscopy,endoscopic microscopy,imaging
Classifier: License :: OSI Approved :: MIT License
Classifier: Programming Language :: Python
Classifier: Programming Language :: Python :: 3
Requires-Python: >=3.8
License-File: LICENSE
Requires-Dist: matplotlib>=3.3.4
Requires-Dist: numba>=0.55.1
Requires-Dist: numpy>=1.22
Requires-Dist: opencv-python>=4.5
Requires-Dist: Pillow>=9
Requires-Dist: scipy>=1.7
